render_watcher/__init__.py
render_watcher/core.py
render_watcher/ui.py
RenderWatcher-0.0.4.dist-info/LICENSE
RenderWatcher-0.0.4.dist-info/METADATA
RenderWatcher-0.0.4.dist-info/WHEEL
RenderWatcher-0.0.4.dist-info/top_level.txt
RenderWatcher-0.0.4.dist-info/RECORD
