Metadata-Version: 2.1
Name: RenderWatcher
Version: 0.0.4
Summary: Render Watcher for Katana jobs
Home-page: UNKNOWN
Author: jlonghurst
Author-email: jlonghurst@thelightersguild.com
License: UNKNOWN
Platform: UNKNOWN
Classifier: Programming Language :: Python :: 3
License-File: LICENSE
